crunch/__init__.py
crunch/client/__init__.py
crunch/client/connections.py
crunch/client/diagnostics.py
crunch/client/enums.py
crunch/client/main.py
crunch/client/run.py
crunch/client/utils.py
crunch/django/__init__.py
crunch/django/app/__init__.py
crunch/django/app/admin.py
crunch/django/app/apps.py
crunch/django/app/enums.py
crunch/django/app/mapping.py
crunch/django/app/models.py
crunch/django/app/serializers.py
crunch/django/app/storages.py
crunch/django/app/tokens.py
crunch/django/app/urls.py
crunch/django/app/views.py
crunch/django/proj/.gitignore
crunch/django/proj/__init__.py
crunch/django/proj/manage.py
crunch/django/proj/settings.py
crunch/django/proj/urls.py
crunch/django/proj/wsgi.py
crunch/management/commands/dataset-files.py
crunch/migrations/0001_initial.py
crunch/migrations/0002_auto_20220320_0535.py
crunch/migrations/0003_booleanattribute.py
crunch/migrations/0004_dateattribute.py
crunch/migrations/0005_alter_item_slug.py
crunch/migrations/0006_filesizeattribute.py
crunch/migrations/0007_dataset_base_file_path.py
crunch/migrations/0008_auto_20220811_1223.py
crunch/migrations/0009_auto_20220811_0231.py
crunch/migrations/0010_auto_20220908_0001.py
crunch/migrations/0011_dataset_locked.py
crunch/migrations/__init__.py
crunch/templates/base.html
crunch/templates/crunch/dataset_detail.html
crunch/templates/crunch/dataset_list.html
crunch/templates/crunch/index.html
crunch/templates/crunch/item_detail.html
crunch/templates/crunch/item_map.html
crunch/templates/crunch/project_detail.html
crunch/templates/crunch/project_list.html
crunch/templatetags/__init__.py
crunch/templatetags/crunch.py
django_crunch-0.1.12.dist-info/entry_points.txt
django_crunch-0.1.12.dist-info/LICENSE.txt
django_crunch-0.1.12.dist-info/WHEEL
django_crunch-0.1.12.dist-info/METADATA
django_crunch-0.1.12.dist-info/RECORD
