Metadata-Version: 2.1
Name: django-crunch
Version: 0.1.12
Summary: A data processing orcestration tool.
Home-page: https://github.com/rbturnbull/django-crunch
License: Apache-2.0
Keywords: django,data processing
Author: Robert Turnbull, Mar Quiroga and Simon Mutch
Author-email: robert.turnbull@unimelb.edu.au
Requires-Python: >=3.8,<=3.11
Classifier: Development Status :: 3 - Alpha
Classifier: Framework :: Django
Classifier: Intended Audience :: Science/Research
Classifier: License :: OSI Approved :: Apache Software License
Classifier: Programming Language :: Python :: 3
Classifier: Programming Language :: Python :: 3.8
Classifier: Programming Language :: Python :: 3.9
Classifier: Programming Language :: Python :: 3.10
Classifier: Programming Language :: Python :: 3.11
Classifier: Topic :: Software Development :: Libraries :: Python Modules
Requires-Dist: Django (>=3.2,<4.0)
Requires-Dist: anytree (>=2.8.0,<3.0.0)
Requires-Dist: django-cms (>=3.9.0,<4.0.0)
Requires-Dist: django-extensions (>=3.1.5,<4.0.0)
Requires-Dist: django-mptt (>=0.13.4,<0.14.0)
Requires-Dist: django-next-prev (>=1.1.0,<2.0.0)
Requires-Dist: django-polymorphic (>=2,<3.1)
Requires-Dist: django-polymorphic-tree (>=2.1,<3.0)
Requires-Dist: django-storages[boto3] (>=1.12.2,<2.0.0)
Requires-Dist: djangocms-admin-style (>=2.0.2,<3.0.0)
Requires-Dist: djangocms-attributes-field (>=2.0.0,<3.0.0)
Requires-Dist: djangocms-bootstrap (>=1.1.2,<2.0.0)
Requires-Dist: djangocms-bootstrap4 (>=2.0.0,<3.0.0)
Requires-Dist: djangocms-file (>=3.0.0,<4.0.0)
Requires-Dist: djangocms-googlemap (>=2.0.0,<3.0.0)
Requires-Dist: djangocms-link (>=3.0.0,<4.0.0)
Requires-Dist: djangocms-page-meta (>=1.0.1,<2.0.0)
Requires-Dist: djangocms-picture (>=3.0.0,<4.0.0)
Requires-Dist: djangocms-snippet (>=3.0.0,<4.0.0)
Requires-Dist: djangocms-style (>=3.0.0,<4.0.0)
Requires-Dist: djangocms-text-ckeditor (>=4.0.0,<5.0.0)
Requires-Dist: djangocms-themata (>=0.1.0,<0.2.0)
Requires-Dist: djangocms-video (>=3.0.0,<4.0.0)
Requires-Dist: djangorestframework (>=3.13.1,<4.0.0)
Requires-Dist: humanize (>=4.0.0,<5.0.0)
Requires-Dist: ipykernel (>=6.9.1,<7.0.0)
Requires-Dist: pandas (>=1.4.4,<2.0.0)
Requires-Dist: pydeck (>=0.7.1,<0.8.0)
Requires-Dist: python-dateutil (>=2.8.2,<3.0.0)
Requires-Dist: requests (>=2.27.1,<3.0.0)
Requires-Dist: rich (>=11.1.0,<12.0.0)
Requires-Dist: setuptools (>=65.3.0,<66.0.0)
Requires-Dist: snakemake (>=6.15.5,<7.0.0)
Requires-Dist: toml (>=0.10.2,<0.11.0)
Requires-Dist: typer[all] (>=0.4.0,<0.5.0)
Project-URL: Documentation, https://rbturnbull.github.io/django-crunch/
Project-URL: Repository, https://github.com/rbturnbull/django-crunch
